{
    "archive_path": "archive/1765136789.545169",
    "base_url": "blog.wesleyac.com/posts/simple-deploy-script",
    "basename": "simple-deploy-script",
    "bookmarked_date": "2025-12-07 19:46",
    "canonical": {
        "archive_org_path": "https://web.archive.org/web/blog.wesleyac.com/posts/simple-deploy-script",
        "dom_path": "output.html",
        "favicon_path": "favicon.ico",
        "git_path": "git/",
        "google_favicon_path": "https://www.google.com/s2/favicons?domain=blog.wesleyac.com",
        "headers_path": "headers.json",
        "index_path": "index.html",
        "media_path": "media/",
        "mercury_path": "mercury/content.html",
        "pdf_path": "output.pdf",
        "readability_path": "readability/content.html",
        "screenshot_path": "screenshot.png",
        "singlefile_path": "singlefile.html",
        "warc_path": "warc/",
        "wget_path": null
    },
    "domain": "blog.wesleyac.com",
    "extension": "",
    "hash": "Y7XE3PGTDTEPXETD2B1A",
    "history": {
        "archive_org": [
            {
                "cmd": [
                    "curl",
                    "--silent",
                    "--location",
                    "--compressed",
                    "--head",
                    "--max-time",
                    "90",
                    "--user-agent",
                    "Mozilla/5.0 (Macintosh; Intel Mac OS X 10_15_7) AppleWebKit/537.36 (KHTML, like Gecko) Chrome/90.0.4430.61 Safari/537.36 ArchiveBox/0.6.2 (+https://github.com/ArchiveBox/ArchiveBox/) curl/curl 7.76.1 (x86_64-pc-linux-gnu)",
                    "https://web.archive.org/save/https://blog.wesleyac.com/posts/simple-deploy-script"
                ],
                "cmd_version": "curl 7.76.1 (x86_64-pc-linux-gnu)",
                "end_ts": "2025-12-07T19:57:08.726620+00:00",
                "index_texts": null,
                "output": "TimeoutExpired: Command '['curl', '--silent', '--location', '--compressed', '--head', '--max-time', '90', '--user-agent', 'Mozilla/5.0 (Macintosh; Intel Mac OS X 10_15_7) AppleWebKit/537.36 (KHTML, like Gecko) Chrome/90.0.4430.61 Safari/537.36 ArchiveBox/0.6.2 (+https://github.com/ArchiveBox/ArchiveBox/) curl/curl 7.76.1 (x86_64-pc-linux-gnu)', 'https://web.archive.org/save/https://blog.wesleyac.com/posts/simple-deploy-script']' timed out after 90 seconds",
                "pwd": "/home/wesleyac/projects/notebook/data/archivebox/archive/1765136789.545169",
                "schema": "ArchiveResult",
                "start_ts": "2025-12-07T19:55:38.713433+00:00",
                "status": "failed"
            }
        ],
        "dom": [
            {
                "cmd": [
                    "chromium-browser",
                    "--headless",
                    "--user-agent=Mozilla/5.0 (Macintosh; Intel Mac OS X 10_15_7) AppleWebKit/537.36 (KHTML, like Gecko) Chrome/90.0.4430.61 Safari/537.36 ArchiveBox/{VERSION} (+https://github.com/ArchiveBox/ArchiveBox/)",
                    "--window-size=1440,2000",
                    "--timeout=90000",
                    "--dump-dom",
                    "https://blog.wesleyac.com/posts/simple-deploy-script"
                ],
                "cmd_version": "Chromium 142.0.7444.175",
                "end_ts": "2025-12-07T19:55:38.701390+00:00",
                "index_texts": null,
                "output": "output.html",
                "pwd": "/home/wesleyac/projects/notebook/data/archivebox/archive/1765136789.545169",
                "schema": "ArchiveResult",
                "start_ts": "2025-12-07T19:55:37.805630+00:00",
                "status": "succeeded"
            }
        ],
        "favicon": [
            {
                "cmd": [
                    "curl",
                    "--silent",
                    "--location",
                    "--compressed",
                    "--max-time",
                    "90",
                    "--output",
                    "favicon.ico",
                    "--user-agent",
                    "Mozilla/5.0 (Macintosh; Intel Mac OS X 10_15_7) AppleWebKit/537.36 (KHTML, like Gecko) Chrome/90.0.4430.61 Safari/537.36 ArchiveBox/0.6.2 (+https://github.com/ArchiveBox/ArchiveBox/) curl/curl 7.76.1 (x86_64-pc-linux-gnu)",
                    "https://www.google.com/s2/favicons?domain=blog.wesleyac.com"
                ],
                "cmd_version": "curl 7.76.1 (x86_64-pc-linux-gnu)",
                "end_ts": "2025-12-07T19:55:30.983814+00:00",
                "index_texts": null,
                "output": "favicon.ico",
                "pwd": "/home/wesleyac/projects/notebook/data/archivebox/archive/1765136789.545169",
                "schema": "ArchiveResult",
                "start_ts": "2025-12-07T19:55:30.791642+00:00",
                "status": "succeeded"
            }
        ],
        "git": [],
        "headers": [
            {
                "cmd": [
                    "curl",
                    "--silent",
                    "--location",
                    "--compressed",
                    "--head",
                    "--max-time",
                    "90",
                    "--user-agent",
                    "Mozilla/5.0 (Macintosh; Intel Mac OS X 10_15_7) AppleWebKit/537.36 (KHTML, like Gecko) Chrome/90.0.4430.61 Safari/537.36 ArchiveBox/0.6.2 (+https://github.com/ArchiveBox/ArchiveBox/) curl/curl 7.76.1 (x86_64-pc-linux-gnu)",
                    "https://blog.wesleyac.com/posts/simple-deploy-script"
                ],
                "cmd_version": "curl 7.76.1 (x86_64-pc-linux-gnu)",
                "end_ts": "2025-12-07T19:55:31.073717+00:00",
                "index_texts": null,
                "output": "headers.json",
                "pwd": "/home/wesleyac/projects/notebook/data/archivebox/archive/1765136789.545169",
                "schema": "ArchiveResult",
                "start_ts": "2025-12-07T19:55:30.998996+00:00",
                "status": "succeeded"
            }
        ],
        "media": [],
        "mercury": [],
        "pdf": [],
        "readability": [],
        "screenshot": [
            {
                "cmd": [
                    "chromium-browser",
                    "--headless",
                    "--user-agent=Mozilla/5.0 (Macintosh; Intel Mac OS X 10_15_7) AppleWebKit/537.36 (KHTML, like Gecko) Chrome/90.0.4430.61 Safari/537.36 ArchiveBox/{VERSION} (+https://github.com/ArchiveBox/ArchiveBox/)",
                    "--window-size=1440,2000",
                    "--timeout=90000",
                    "--screenshot",
                    "https://blog.wesleyac.com/posts/simple-deploy-script"
                ],
                "cmd_version": "Chromium 142.0.7444.175",
                "end_ts": "2025-12-07T19:55:37.793771+00:00",
                "index_texts": null,
                "output": "screenshot.png",
                "pwd": "/home/wesleyac/projects/notebook/data/archivebox/archive/1765136789.545169",
                "schema": "ArchiveResult",
                "start_ts": "2025-12-07T19:55:36.712459+00:00",
                "status": "succeeded"
            }
        ],
        "singlefile": [
            {
                "cmd": [
                    "/home/wesleyac/projects/notebook/data/archivebox/node_modules/single-file/cli/single-file",
                    "--browser-executable-path=chromium-browser",
                    "--browser-args=[\"--headless\", \"--user-agent=Mozilla/5.0 (Macintosh; Intel Mac OS X 10_15_7) AppleWebKit/537.36 (KHTML, like Gecko) Chrome/90.0.4430.61 Safari/537.36 ArchiveBox/{VERSION} (+https://github.com/ArchiveBox/ArchiveBox/)\", \"--window-size=1440,2000\"]",
                    "https://blog.wesleyac.com/posts/simple-deploy-script",
                    "singlefile.html"
                ],
                "cmd_version": "0.3.31",
                "end_ts": "2025-12-07T19:55:36.701068+00:00",
                "index_texts": null,
                "output": "singlefile.html",
                "pwd": "/home/wesleyac/projects/notebook/data/archivebox/archive/1765136789.545169",
                "schema": "ArchiveResult",
                "start_ts": "2025-12-07T19:55:31.089398+00:00",
                "status": "succeeded"
            }
        ],
        "title": [
            {
                "cmd": [
                    "curl",
                    "--silent",
                    "--location",
                    "--compressed",
                    "--max-time",
                    "90",
                    "--user-agent",
                    "Mozilla/5.0 (Macintosh; Intel Mac OS X 10_15_7) AppleWebKit/537.36 (KHTML, like Gecko) Chrome/90.0.4430.61 Safari/537.36 ArchiveBox/0.6.2 (+https://github.com/ArchiveBox/ArchiveBox/) curl/curl 7.76.1 (x86_64-pc-linux-gnu)",
                    "https://blog.wesleyac.com/posts/simple-deploy-script"
                ],
                "cmd_version": "curl 7.76.1 (x86_64-pc-linux-gnu)",
                "end_ts": "2025-12-07T19:55:30.776215+00:00",
                "index_texts": null,
                "output": "Wesley Aptekar-Cassels | A simple but safe deploy script",
                "pwd": "/home/wesleyac/projects/notebook/data/archivebox/archive/1765136789.545169",
                "schema": "ArchiveResult",
                "start_ts": "2025-12-07T19:55:30.539461+00:00",
                "status": "succeeded"
            }
        ],
        "wget": []
    },
    "icons": null,
    "is_archived": true,
    "is_static": false,
    "latest": {
        "archive_org": "TimeoutExpired: Command '['curl', '--silent', '--location', '--compressed', '--head', '--max-time', '90', '--user-agent', 'Mozilla/5.0 (Macintosh; Intel Mac OS X 10_15_7) AppleWebKit/537.36 (KHTML, like Gecko) Chrome/90.0.4430.61 Safari/537.36 ArchiveBox/0.6.2 (+https://github.com/ArchiveBox/ArchiveBox/) curl/curl 7.76.1 (x86_64-pc-linux-gnu)', 'https://web.archive.org/save/https://blog.wesleyac.com/posts/simple-deploy-script']' timed out after 90 seconds",
        "dom": "output.html",
        "favicon": "favicon.ico",
        "git": null,
        "media": null,
        "pdf": null,
        "screenshot": "screenshot.png",
        "singlefile": "singlefile.html",
        "title": "Wesley Aptekar-Cassels | A simple but safe deploy script",
        "warc": null,
        "wget": null
    },
    "link_dir": "/home/wesleyac/projects/notebook/data/archivebox/archive/1765136789.545169",
    "newest_archive_date": "2025-12-07T19:55:38.713433+00:00",
    "num_failures": 1,
    "num_outputs": 6,
    "oldest_archive_date": "2025-12-07T19:55:30.539461+00:00",
    "path": "/posts/simple-deploy-script",
    "schema": "Link",
    "scheme": "https",
    "snapshot_id": "ef9ce327-5bc6-4735-b75e-037938243a62",
    "sources": [
        "/home/wesleyac/projects/notebook/data/archivebox/sources/1765136789-import.txt"
    ],
    "tags": null,
    "tags_str": "",
    "timestamp": "1765136789.545169",
    "title": "Wesley Aptekar-Cassels | A simple but safe deploy script",
    "updated": "2025-12-07T19:55:30.535976+00:00",
    "updated_date": "2025-12-07 19:55",
    "url": "https://blog.wesleyac.com/posts/simple-deploy-script"
}